{
  "title": "Il Trono di Spade: Libro secondo delle cronache del ghiaccio e del fuoco",
  "isbn": "8804630736",
  "isbn13": "9788804630739",
	"synopsis": "",
  "author": [
    "George R. R. Martin"
  ],
  "genres": [
    "Fantasy"
  ],
  "ogPublishedYear": 1998,
  "pages": 963,
  "format": "Hardcover",
  "publisher": "Mondadori",
  "rating": 5,
  "image": "TronoDiSpade_2.jpg",
	"reviewSlug": "recensione-il-trono-di-spade-libro-secondo-george-martin",
  "readDate": "12-04-2019",
  "publishedYear": 2013,
  "series": [{"series": "Il Trono di Spade", "numInSeries": 2},{"series": "Cronache del ghiaccio e del fuoco", "numInSeries": 2}]
}