[{"title":"Recensione \"Watchmen\" di Alan Moore e Dave Gibbons","image":"/static/images/books/Watchmen.jpg","slug":"recensione-watchmen-alan-moore"},{"title":"Recensione \"Il Trono di Spade: Libro terzo delle cronache del ghiaccio e del fuoco\" di George R. R. Martin","image":"/static/images/books/TdS_3.jpg","slug":"recensione-il-trono-di-spade-libro-terzo-george-martin"},{"title":"Recensione \"Il trono di spade. Libro primo delle Cronache del ghiaccio e del fuoco\" di George R. R. Martin","image":"/static/images/books/TronoDiSpade_1.jpg","slug":"recensione-il-trono-di-spade-libro-primo-george-martin"},{"title":"Recensione \"Orfani\" di Roberto Recchioni e Emiliano Mammucari","image":"/static/images/books/Orfani1.jpg","slug":"recensione-orfani"}]