[{"title":"Recensione \"Il priorato dell'albero delle arance\" di Samantha Shannon","image":"/static/images/books/Il Priorato.jpg","slug":"recensione-il-priorato-dellalbero-delle-arance-samantha-shannon"},{"title":"Recensione \"L'ascesa di Senlin\" di Josiah Bancroft","image":"/static/images/books/L_Ascesa di Senlin.jpg","slug":"recensione-ascesa-di-senlin-josiah-bancroft"},{"title":"Recensione \"Crooked Kingdom\" di Leigh Bardugo","image":"/static/images/books/CrookedKingdom.jpg","slug":"recensione-crooked-kingdom-leigh-bardugo"},{"title":"Recensione \"Six of Crows\" di Leigh Bardugo","image":"/static/images/books/SixOfCrows.jpg","slug":"recensione-six-of-crows-bardugo"}]